callbacker-0.1.0.dist-info/METADATA
callbacker-0.1.0.dist-info/WHEEL
callbacker-0.1.0.dist-info/entry_points.txt
callbacker-0.1.0.dist-info/licenses/LICENSE
callbacker/__init__.py
callbacker/callback.py
callbacker/signal.py
callbacker-0.1.0.dist-info/RECORD
