Metadata-Version: 2.1
Name: callbacker
Version: 0.1.0
Summary: Callback library for sync/async python
Author-Email: ipfans <363344+ipfans@users.noreply.github.com>
License: MIT
Requires-Python: >=3.11
Requires-Dist: frozenlist>=1.5.0
Provides-Extra: dev
Requires-Dist: pytest>=8.3.4; extra == "dev"
Requires-Dist: ruff>=0.8.4; extra == "dev"
Requires-Dist: flake8>=7.1.1; extra == "dev"
Requires-Dist: black>=24.10.0; extra == "dev"
Requires-Dist: mypy>=1.14.1; extra == "dev"
